{
    "__typename": "PlayerScorecardStats",
    "id": "R2023480-39067",
    "rounds": [
        {
            "__typename": "PlayerScorecardRoundStats",
            "round": "-1",
            "displayName": "All",
            "roundStatus": "UPCOMING",
            "performance": [
                {
                    "label": "SG: Off The Tee",
                    "rank": "T32",
                    "total": "1.289",
                    "yearToDate": "0.571",
                    "statId": "02567"
                },
                {
                    "label": "SG: Approach to Green",
                    "rank": "44",
                    "total": "1.025",
                    "yearToDate": "-0.374",
                    "statId": "02568"
                },
                {
                    "label": "SG: Around The Green",
                    "rank": "45",
                    "total": "-0.215",
                    "yearToDate": "-0.199",
                    "statId": "02569"
                },
                {
                    "label": "SG: Putting",
                    "rank": "45",
                    "total": "-0.429",
                    "yearToDate": "-0.209",
                    "statId": "02564"
                },
                {
                    "label": "SG: Total",
                    "rank": "T47",
                    "total": "0.490",
                    "yearToDate": "-0.211",
                    "statId": "02675"
                },
                {
                    "label": "Driving Accuracy",
                    "total": "42.86% (24/56)",
                    "rank": "T60",
                    "yearToDate": "58.46%",
                    "statId": "102"
                },
                {
                    "label": "Driving Distance",
                    "total": "322.40 yds",
                    "rank": "15",
                    "yearToDate": "310.5",
                    "statId": "101"
                },
                {
                    "label": "Longest Drive",
                    "total": "344.00 yds",
                    "rank": "T76",
                    "yearToDate": "407",
                    "statId": "159"
                },
                {
                    "label": "Greens in Regulation",
                    "total": "68.06% (49/72)",
                    "rank": "T29",
                    "yearToDate": "66.99%",
                    "statId": "103"
                },
                {
                    "label": "Sand Saves",
                    "total": "37.50% (3/8)",
                    "rank": "T55",
                    "yearToDate": "51.50%",
                    "statId": "111"
                },
                {
                    "label": "Scrambling",
                    "total": "43.48% (10/23)",
                    "rank": "64",
                    "yearToDate": "57.68%",
                    "statId": "130"
                },
                {
                    "label": "Putts per GIR",
                    "total": "1.74",
                    "rank": "24",
                    "yearToDate": "1.779",
                    "statId": "104"
                }
            ],
            "scoring": [
                {
                    "__typename": "ScorecardStatsItem",
                    "label": "Eagles -",
                    "total": "0",
                    "rank": "T30",
                    "yearToDate": "10",
                    "statId": "106"
                },
                {
                    "__typename": "ScorecardStatsItem",
                    "label": "Birdies",
                    "total": "18",
                    "rank": "T7",
                    "yearToDate": "415",
                    "statId": "107"
                },
                {
                    "__typename": "ScorecardStatsItem",
                    "label": "Pars",
                    "total": "40",
                    "rank": "T59",
                    "yearToDate": "-",
                    "statId": "1005"
                },
                {
                    "__typename": "ScorecardStatsItem",
                    "label": "Bogeys",
                    "total": "12",
                    "rank": "T46",
                    "yearToDate": "-",
                    "statId": "1002"
                },
                {
                    "__typename": "ScorecardStatsItem",
                    "label": "Double Bogeys",
                    "total": "1",
                    "rank": "T25",
                    "yearToDate": "-",
                    "statId": "1003"
                }
            ],
            "strokesGained": [
                {
                    "__typename": "StrokesGainedStats",
                    "statId": "02567",
                    "graph": true,
                    "label": "SG: Off The Tee",
                    "shortLabel": "Off The Tee",
                    "total": "1.289",
                    "totalNum": 1.289,
                    "rank": "T32",
                    "yearToDate": "0.571",
                    "yearToDateNum": 0.571
                },
                {
                    "__typename": "StrokesGainedStats",
                    "statId": "02568",
                    "graph": true,
                    "label": "SG: Approach to Green",
                    "shortLabel": "Approach to Green",
                    "total": "1.025",
                    "totalNum": 1.025,
                    "rank": "44",
                    "yearToDate": "-0.374",
                    "yearToDateNum": -0.374
                },
                {
                    "__typename": "StrokesGainedStats",
                    "statId": "02569",
                    "graph": true,
                    "label": "SG: Around The Green",
                    "shortLabel": "Around The Green",
                    "total": "-0.215",
                    "totalNum": -0.215,
                    "rank": "45",
                    "yearToDate": "-0.199",
                    "yearToDateNum": -0.199
                },
                {
                    "__typename": "StrokesGainedStats",
                    "statId": "02564",
                    "graph": true,
                    "label": "SG: Putting",
                    "shortLabel": "Putting",
                    "total": "-0.429",
                    "totalNum": -0.429,
                    "rank": "45",
                    "yearToDate": "-0.209",
                    "yearToDateNum": -0.209
                },
                {
                    "__typename": "StrokesGainedStats",
                    "statId": "02675",
                    "graph": false,
                    "label": "SG: Total",
                    "shortLabel": "Total",
                    "total": "0.490",
                    "totalNum": 0.49,
                    "rank": "T47",
                    "yearToDate": "-0.211",
                    "yearToDateNum": -0.211
                }
            ]
        },
        {
            "__typename": "PlayerScorecardRoundStats",
            "round": "4",
            "displayName": "Round 4",
            "roundStatus": "OFFICIAL",
            "performance": [
                {
                    "label": "SG: Off The Tee",
                    "rank": "37",
                    "total": "-0.081",
                    "yearToDate": "0.571",
                    "statId": "02567"
                },
                {
                    "label": "SG: Approach to Green",
                    "rank": "49",
                    "total": "-0.784",
                    "yearToDate": "-0.374",
                    "statId": "02568"
                },
                {
                    "label": "SG: Around The Green",
                    "rank": "32",
                    "total": "0.099",
                    "yearToDate": "-0.199",
                    "statId": "02569"
                },
                {
                    "label": "SG: Putting",
                    "rank": "66",
                    "total": "-2.584",
                    "yearToDate": "-0.209",
                    "statId": "02564"
                },
                {
                    "label": "SG: Total",
                    "rank": "T56",
                    "total": "-2.485",
                    "yearToDate": "-0.211",
                    "statId": "02675"
                },
                {
                    "label": "Driving Accuracy",
                    "total": "50.00% (7/14)",
                    "rank": "T35",
                    "yearToDate": "58.46%",
                    "statId": "102"
                },
                {
                    "label": "Driving Distance",
                    "total": "318.00 yds",
                    "rank": "T43",
                    "yearToDate": "310.5",
                    "statId": "101"
                },
                {
                    "label": "Longest Drive",
                    "total": "0.00 yds",
                    "rank": "-",
                    "yearToDate": "407",
                    "statId": "159"
                },
                {
                    "label": "Greens in Regulation",
                    "total": "61.11% (11/18)",
                    "rank": "T37",
                    "yearToDate": "66.99%",
                    "statId": "103"
                },
                {
                    "label": "Sand Saves",
                    "total": "0.00% (0/3)",
                    "rank": "T58",
                    "yearToDate": "51.50%",
                    "statId": "111"
                },
                {
                    "label": "Scrambling",
                    "total": "14.29% (1/7)",
                    "rank": "67",
                    "yearToDate": "57.68%",
                    "statId": "130"
                },
                {
                    "label": "Putts per GIR",
                    "total": "1.73",
                    "rank": "T17",
                    "yearToDate": "1.779",
                    "statId": "104"
                }
            ],
            "scoring": [
                {
                    "__typename": "ScorecardStatsItem",
                    "label": "Eagles -",
                    "total": "0",
                    "rank": "T11",
                    "yearToDate": "10",
                    "statId": "106"
                },
                {
                    "__typename": "ScorecardStatsItem",
                    "label": "Birdies",
                    "total": "4",
                    "rank": "T9",
                    "yearToDate": "415",
                    "statId": "107"
                },
                {
                    "__typename": "ScorecardStatsItem",
                    "label": "Pars",
                    "total": "7",
                    "rank": "T66",
                    "yearToDate": "-",
                    "statId": "1005"
                },
                {
                    "__typename": "ScorecardStatsItem",
                    "label": "Bogeys",
                    "total": "7",
                    "rank": "68",
                    "yearToDate": "-",
                    "statId": "1002"
                },
                {
                    "__typename": "ScorecardStatsItem",
                    "label": "Double Bogeys",
                    "total": "0",
                    "rank": "T1",
                    "yearToDate": "-",
                    "statId": "1003"
                }
            ],
            "strokesGained": [
                {
                    "__typename": "StrokesGainedStats",
                    "statId": "02567",
                    "graph": true,
                    "label": "SG: Off The Tee",
                    "shortLabel": "Off The Tee",
                    "total": "-0.081",
                    "totalNum": -0.081,
                    "rank": "37",
                    "yearToDate": "0.571",
                    "yearToDateNum": 0.571
                },
                {
                    "__typename": "StrokesGainedStats",
                    "statId": "02568",
                    "graph": true,
                    "label": "SG: Approach to Green",
                    "shortLabel": "Approach to Green",
                    "total": "-0.784",
                    "totalNum": -0.784,
                    "rank": "49",
                    "yearToDate": "-0.374",
                    "yearToDateNum": -0.374
                },
                {
                    "__typename": "StrokesGainedStats",
                    "statId": "02569",
                    "graph": true,
                    "label": "SG: Around The Green",
                    "shortLabel": "Around The Green",
                    "total": "0.099",
                    "totalNum": 0.099,
                    "rank": "32",
                    "yearToDate": "-0.199",
                    "yearToDateNum": -0.199
                },
                {
                    "__typename": "StrokesGainedStats",
                    "statId": "02564",
                    "graph": true,
                    "label": "SG: Putting",
                    "shortLabel": "Putting",
                    "total": "-2.584",
                    "totalNum": -2.584,
                    "rank": "66",
                    "yearToDate": "-0.209",
                    "yearToDateNum": -0.209
                },
                {
                    "__typename": "StrokesGainedStats",
                    "statId": "02675",
                    "graph": false,
                    "label": "SG: Total",
                    "shortLabel": "Total",
                    "total": "-2.485",
                    "totalNum": -2.485,
                    "rank": "T56",
                    "yearToDate": "-0.211",
                    "yearToDateNum": -0.211
                }
            ]
        },
        {
            "__typename": "PlayerScorecardRoundStats",
            "round": "3",
            "displayName": "Round 3",
            "roundStatus": "OFFICIAL",
            "performance": [
                {
                    "label": "SG: Off The Tee",
                    "rank": "43",
                    "total": "-0.214",
                    "yearToDate": "0.571",
                    "statId": "02567"
                },
                {
                    "label": "SG: Approach to Green",
                    "rank": "23",
                    "total": "0.801",
                    "yearToDate": "-0.374",
                    "statId": "02568"
                },
                {
                    "label": "SG: Around The Green",
                    "rank": "53",
                    "total": "-1.031",
                    "yearToDate": "-0.199",
                    "statId": "02569"
                },
                {
                    "label": "SG: Putting",
                    "rank": "17",
                    "total": "1.343",
                    "yearToDate": "-0.209",
                    "statId": "02564"
                },
                {
                    "label": "SG: Total",
                    "rank": "T28",
                    "total": "0.176",
                    "yearToDate": "-0.211",
                    "statId": "02675"
                },
                {
                    "label": "Driving Accuracy",
                    "total": "28.57% (4/14)",
                    "rank": "T65",
                    "yearToDate": "58.46%",
                    "statId": "102"
                },
                {
                    "label": "Driving Distance",
                    "total": "330.00 yds",
                    "rank": "13",
                    "yearToDate": "310.5",
                    "statId": "101"
                },
                {
                    "label": "Longest Drive",
                    "total": "0.00 yds",
                    "rank": "-",
                    "yearToDate": "407",
                    "statId": "159"
                },
                {
                    "label": "Greens in Regulation",
                    "total": "66.67% (12/18)",
                    "rank": "T31",
                    "yearToDate": "66.99%",
                    "statId": "103"
                },
                {
                    "label": "Sand Saves",
                    "total": "50.00% (1/2)",
                    "rank": "T29",
                    "yearToDate": "51.50%",
                    "statId": "111"
                },
                {
                    "label": "Scrambling",
                    "total": "50.00% (3/6)",
                    "rank": "T37",
                    "yearToDate": "57.68%",
                    "statId": "130"
                },
                {
                    "label": "Putts per GIR",
                    "total": "1.75",
                    "rank": "T39",
                    "yearToDate": "1.779",
                    "statId": "104"
                }
            ],
            "scoring": [
                {
                    "__typename": "ScorecardStatsItem",
                    "label": "Eagles -",
                    "total": "0",
                    "rank": "T5",
                    "yearToDate": "10",
                    "statId": "106"
                },
                {
                    "__typename": "ScorecardStatsItem",
                    "label": "Birdies",
                    "total": "4",
                    "rank": "T30",
                    "yearToDate": "415",
                    "statId": "107"
                },
                {
                    "__typename": "ScorecardStatsItem",
                    "label": "Pars",
                    "total": "11",
                    "rank": "T25",
                    "yearToDate": "-",
                    "statId": "1005"
                },
                {
                    "__typename": "ScorecardStatsItem",
                    "label": "Bogeys",
                    "total": "3",
                    "rank": "T30",
                    "yearToDate": "-",
                    "statId": "1002"
                },
                {
                    "__typename": "ScorecardStatsItem",
                    "label": "Double Bogeys",
                    "total": "0",
                    "rank": "T1",
                    "yearToDate": "-",
                    "statId": "1003"
                }
            ],
            "strokesGained": [
                {
                    "__typename": "StrokesGainedStats",
                    "statId": "02567",
                    "graph": true,
                    "label": "SG: Off The Tee",
                    "shortLabel": "Off The Tee",
                    "total": "-0.214",
                    "totalNum": -0.214,
                    "rank": "43",
                    "yearToDate": "0.571",
                    "yearToDateNum": 0.571
                },
                {
                    "__typename": "StrokesGainedStats",
                    "statId": "02568",
                    "graph": true,
                    "label": "SG: Approach to Green",
                    "shortLabel": "Approach to Green",
                    "total": "0.801",
                    "totalNum": 0.801,
                    "rank": "23",
                    "yearToDate": "-0.374",
                    "yearToDateNum": -0.374
                },
                {
                    "__typename": "StrokesGainedStats",
                    "statId": "02569",
                    "graph": true,
                    "label": "SG: Around The Green",
                    "shortLabel": "Around The Green",
                    "total": "-1.031",
                    "totalNum": -1.031,
                    "rank": "53",
                    "yearToDate": "-0.199",
                    "yearToDateNum": -0.199
                },
                {
                    "__typename": "StrokesGainedStats",
                    "statId": "02564",
                    "graph": true,
                    "label": "SG: Putting",
                    "shortLabel": "Putting",
                    "total": "1.343",
                    "totalNum": 1.343,
                    "rank": "17",
                    "yearToDate": "-0.209",
                    "yearToDateNum": -0.209
                },
                {
                    "__typename": "StrokesGainedStats",
                    "statId": "02675",
                    "graph": false,
                    "label": "SG: Total",
                    "shortLabel": "Total",
                    "total": "0.176",
                    "totalNum": 0.176,
                    "rank": "T28",
                    "yearToDate": "-0.211",
                    "yearToDateNum": -0.211
                }
            ]
        },
        {
            "__typename": "PlayerScorecardRoundStats",
            "round": "2",
            "displayName": "Round 2",
            "roundStatus": "OFFICIAL",
            "performance": [
                {
                    "label": "SG: Off The Tee",
                    "rank": "114",
                    "total": "-0.530",
                    "yearToDate": "0.571",
                    "statId": "02567"
                },
                {
                    "label": "SG: Approach to Green",
                    "rank": "75",
                    "total": "-0.067",
                    "yearToDate": "-0.374",
                    "statId": "02568"
                },
                {
                    "label": "SG: Around The Green",
                    "rank": "9",
                    "total": "1.867",
                    "yearToDate": "-0.199",
                    "statId": "02569"
                },
                {
                    "label": "SG: Putting",
                    "rank": "60",
                    "total": "0.496",
                    "yearToDate": "-0.209",
                    "statId": "02564"
                },
                {
                    "label": "SG: Total",
                    "rank": "T49",
                    "total": "1.078",
                    "yearToDate": "-0.211",
                    "statId": "02675"
                },
                {
                    "label": "Driving Accuracy",
                    "total": "42.86% (6/14)",
                    "rank": "T113",
                    "yearToDate": "58.46%",
                    "statId": "102"
                },
                {
                    "label": "Driving Distance",
                    "total": "316.50 yds",
                    "rank": "T31",
                    "yearToDate": "310.5",
                    "statId": "101"
                },
                {
                    "label": "Longest Drive",
                    "total": "0.00 yds",
                    "rank": "-",
                    "yearToDate": "407",
                    "statId": "159"
                },
                {
                    "label": "Greens in Regulation",
                    "total": "61.11% (11/18)",
                    "rank": "T76",
                    "yearToDate": "66.99%",
                    "statId": "103"
                },
                {
                    "label": "Sand Saves",
                    "total": "100.00% (1/1)",
                    "rank": "T1",
                    "yearToDate": "51.50%",
                    "statId": "111"
                },
                {
                    "label": "Scrambling",
                    "total": "57.14% (4/7)",
                    "rank": "T66",
                    "yearToDate": "57.68%",
                    "statId": "130"
                },
                {
                    "label": "Putts per GIR",
                    "total": "1.64",
                    "rank": "T28",
                    "yearToDate": "1.779",
                    "statId": "104"
                }
            ],
            "scoring": [
                {
                    "__typename": "ScorecardStatsItem",
                    "label": "Eagles -",
                    "total": "0",
                    "rank": "T15",
                    "yearToDate": "10",
                    "statId": "106"
                },
                {
                    "__typename": "ScorecardStatsItem",
                    "label": "Birdies",
                    "total": "5",
                    "rank": "T14",
                    "yearToDate": "415",
                    "statId": "107"
                },
                {
                    "__typename": "ScorecardStatsItem",
                    "label": "Pars",
                    "total": "10",
                    "rank": "T101",
                    "yearToDate": "-",
                    "statId": "1005"
                },
                {
                    "__typename": "ScorecardStatsItem",
                    "label": "Bogeys",
                    "total": "2",
                    "rank": "T37",
                    "yearToDate": "-",
                    "statId": "1002"
                },
                {
                    "__typename": "ScorecardStatsItem",
                    "label": "Double Bogeys",
                    "total": "1",
                    "rank": "T112",
                    "yearToDate": "-",
                    "statId": "1003"
                }
            ],
            "strokesGained": [
                {
                    "__typename": "StrokesGainedStats",
                    "statId": "02567",
                    "graph": true,
                    "label": "SG: Off The Tee",
                    "shortLabel": "Off The Tee",
                    "total": "-0.530",
                    "totalNum": -0.53,
                    "rank": "114",
                    "yearToDate": "0.571",
                    "yearToDateNum": 0.571
                },
                {
                    "__typename": "StrokesGainedStats",
                    "statId": "02568",
                    "graph": true,
                    "label": "SG: Approach to Green",
                    "shortLabel": "Approach to Green",
                    "total": "-0.067",
                    "totalNum": -0.067,
                    "rank": "75",
                    "yearToDate": "-0.374",
                    "yearToDateNum": -0.374
                },
                {
                    "__typename": "StrokesGainedStats",
                    "statId": "02569",
                    "graph": true,
                    "label": "SG: Around The Green",
                    "shortLabel": "Around The Green",
                    "total": "1.867",
                    "totalNum": 1.867,
                    "rank": "9",
                    "yearToDate": "-0.199",
                    "yearToDateNum": -0.199
                },
                {
                    "__typename": "StrokesGainedStats",
                    "statId": "02564",
                    "graph": true,
                    "label": "SG: Putting",
                    "shortLabel": "Putting",
                    "total": "0.496",
                    "totalNum": 0.496,
                    "rank": "60",
                    "yearToDate": "-0.209",
                    "yearToDateNum": -0.209
                },
                {
                    "__typename": "StrokesGainedStats",
                    "statId": "02675",
                    "graph": false,
                    "label": "SG: Total",
                    "shortLabel": "Total",
                    "total": "1.078",
                    "totalNum": 1.078,
                    "rank": "T49",
                    "yearToDate": "-0.211",
                    "yearToDateNum": -0.211
                }
            ]
        },
        {
            "__typename": "PlayerScorecardRoundStats",
            "round": "1",
            "displayName": "Round 1",
            "roundStatus": "OFFICIAL",
            "performance": [
                {
                    "label": "SG: Off The Tee",
                    "rank": "4",
                    "total": "2.113",
                    "yearToDate": "0.571",
                    "statId": "02567"
                },
                {
                    "label": "SG: Approach to Green",
                    "rank": "40",
                    "total": "1.075",
                    "yearToDate": "-0.374",
                    "statId": "02568"
                },
                {
                    "label": "SG: Around The Green",
                    "rank": "134",
                    "total": "-1.150",
                    "yearToDate": "-0.199",
                    "statId": "02569"
                },
                {
                    "label": "SG: Putting",
                    "rank": "73",
                    "total": "0.315",
                    "yearToDate": "-0.209",
                    "statId": "02564"
                },
                {
                    "label": "SG: Total",
                    "rank": "T36",
                    "total": "1.721",
                    "yearToDate": "-0.211",
                    "statId": "02675"
                },
                {
                    "label": "Driving Accuracy",
                    "total": "50.00% (7/14)",
                    "rank": "T78",
                    "yearToDate": "58.46%",
                    "statId": "102"
                },
                {
                    "label": "Driving Distance",
                    "total": "325.00 yds",
                    "rank": "T29",
                    "yearToDate": "310.5",
                    "statId": "101"
                },
                {
                    "label": "Longest Drive",
                    "total": "344.00 yds",
                    "rank": "T40",
                    "yearToDate": "407",
                    "statId": "159"
                },
                {
                    "label": "Greens in Regulation",
                    "total": "83.33% (15/18)",
                    "rank": "T2",
                    "yearToDate": "66.99%",
                    "statId": "103"
                },
                {
                    "label": "Sand Saves",
                    "total": "50.00% (1/2)",
                    "rank": "T51",
                    "yearToDate": "51.50%",
                    "statId": "111"
                },
                {
                    "label": "Scrambling",
                    "total": "66.67% (2/3)",
                    "rank": "T39",
                    "yearToDate": "57.68%",
                    "statId": "130"
                },
                {
                    "label": "Putts per GIR",
                    "total": "1.80",
                    "rank": "T75",
                    "yearToDate": "1.779",
                    "statId": "104"
                }
            ],
            "scoring": [
                {
                    "__typename": "ScorecardStatsItem",
                    "label": "Eagles -",
                    "total": "0",
                    "rank": "T15",
                    "yearToDate": "10",
                    "statId": "106"
                },
                {
                    "__typename": "ScorecardStatsItem",
                    "label": "Birdies",
                    "total": "5",
                    "rank": "T14",
                    "yearToDate": "415",
                    "statId": "107"
                },
                {
                    "__typename": "ScorecardStatsItem",
                    "label": "Pars",
                    "total": "12",
                    "rank": "T33",
                    "yearToDate": "-",
                    "statId": "1005"
                },
                {
                    "__typename": "ScorecardStatsItem",
                    "label": "Bogeys",
                    "total": "0",
                    "rank": "T1",
                    "yearToDate": "-",
                    "statId": "1002"
                },
                {
                    "__typename": "ScorecardStatsItem",
                    "label": "Double Bogeys",
                    "total": "0",
                    "rank": "T1",
                    "yearToDate": "-",
                    "statId": "1003"
                }
            ],
            "strokesGained": [
                {
                    "__typename": "StrokesGainedStats",
                    "statId": "02567",
                    "graph": true,
                    "label": "SG: Off The Tee",
                    "shortLabel": "Off The Tee",
                    "total": "2.113",
                    "totalNum": 2.113,
                    "rank": "4",
                    "yearToDate": "0.571",
                    "yearToDateNum": 0.571
                },
                {
                    "__typename": "StrokesGainedStats",
                    "statId": "02568",
                    "graph": true,
                    "label": "SG: Approach to Green",
                    "shortLabel": "Approach to Green",
                    "total": "1.075",
                    "totalNum": 1.075,
                    "rank": "40",
                    "yearToDate": "-0.374",
                    "yearToDateNum": -0.374
                },
                {
                    "__typename": "StrokesGainedStats",
                    "statId": "02569",
                    "graph": true,
                    "label": "SG: Around The Green",
                    "shortLabel": "Around The Green",
                    "total": "-1.150",
                    "totalNum": -1.15,
                    "rank": "134",
                    "yearToDate": "-0.199",
                    "yearToDateNum": -0.199
                },
                {
                    "__typename": "StrokesGainedStats",
                    "statId": "02564",
                    "graph": true,
                    "label": "SG: Putting",
                    "shortLabel": "Putting",
                    "total": "0.315",
                    "totalNum": 0.315,
                    "rank": "73",
                    "yearToDate": "-0.209",
                    "yearToDateNum": -0.209
                },
                {
                    "__typename": "StrokesGainedStats",
                    "statId": "02675",
                    "graph": false,
                    "label": "SG: Total",
                    "shortLabel": "Total",
                    "total": "1.721",
                    "totalNum": 1.721,
                    "rank": "T36",
                    "yearToDate": "-0.211",
                    "yearToDateNum": -0.211
                }
            ]
        }
    ]
}